canarypy_airflow_plugin/__init__.py
canarypy_airflow_plugin/canarypy_plugin.py
canarypy_airflow_plugin-0.0.1.dist-info/METADATA
canarypy_airflow_plugin-0.0.1.dist-info/WHEEL
canarypy_airflow_plugin-0.0.1.dist-info/entry_points.txt
canarypy_airflow_plugin-0.0.1.dist-info/top_level.txt
canarypy_airflow_plugin-0.0.1.dist-info/RECORD
