Metadata-Version: 2.1
Name: canarypy-airflow-plugin
Version: 0.0.1
Summary: CanaryPy Airflow Plugin - Airflow Integration Plugin for CanaryPy
Home-page: https://github.com/thcidale0808/canarypy
Author: Thiago Assumpcao
Author-email: thcidale@gmail.com
License: UNKNOWN
Project-URL: Bug Reports, https://github.com/thcidale0808/canarypy/issues
Project-URL: Source, https://github.com/thcidale0808/canarypy/
Platform: UNKNOWN
Classifier: Development Status :: 3 - Alpha
Classifier: Intended Audience :: Developers
Classifier: Topic :: Software Development :: Build Tools
Classifier: License :: OSI Approved :: MIT License
Classifier: Programming Language :: Python :: 3.8
Classifier: Programming Language :: Python :: 3.9
Classifier: Programming Language :: Python :: 3.10
Classifier: Programming Language :: Python :: 3.11
Requires-Python: >=3.8
Requires-Dist: apache-airflow (>=2.0.2)
Requires-Dist: canarypy
